[
	{
		"name": "com.github.benmanes.caffeine.cache.SSLMSW",
		"allPublicConstructors": true,
		"allDeclaredConstructors": true
	},
	{
		"name": "com.github.benmanes.caffeine.cache.SSLMSA",
		"allPublicConstructors": true,
		"allDeclaredConstructors": true
	},
	{
		"name": "br.com.base.records.UserResponse",
		"allDeclaredFields": true,
		"allDeclaredMethods": true,
		"allDeclaredConstructors": true
	},
	{
		"name": "br.com.base.exception.ExceptionBody",
		"allDeclaredFields": true,
		"allDeclaredMethods": true,
		"allDeclaredConstructors": true
	}
]